README.rst
setup.py
use_payment/__init__.py
use_payment.egg-info/PKG-INFO
use_payment.egg-info/SOURCES.txt
use_payment.egg-info/dependency_links.txt
use_payment.egg-info/requires.txt
use_payment.egg-info/top_level.txt
use_payment/alipay/__init__.py
use_payment/alipay/alipay.py
use_payment/alipay/notify.py
use_payment/encrypt/__init__.py
use_payment/encrypt/aes_encrypt.py
use_payment/encrypt/rsa_encrypt.py
use_payment/exceptions/__init__.py
use_payment/exceptions/exceptions.py
use_payment/params/__init__.py
use_payment/params/params.py
use_payment/weipay/__init__.py
use_payment/weipay/notify.py
use_payment/weipay/v3_cert.py
use_payment/weipay/weipay.py