Metadata-Version: 2.1
Name: use-payment
Version: 0.5
Summary: 支持支付宝和微信支付的支付模块
Home-page: https://www.leetab.com
Author: Ryan
Author-email: 604729765@qq.com
License: UNKNOWN
Platform: UNKNOWN
